qhrf_backend_selector/__init__.py
qhrf_backend_selector/cli.py
qhrf_backend_selector/selector.py
qhrf_backend_selector/utils.py
qhrf_backend_selector-1.1.0.dist-info/licenses/LICENSE
qhrf_backend_selector-1.1.0.dist-info/METADATA
qhrf_backend_selector-1.1.0.dist-info/WHEEL
qhrf_backend_selector-1.1.0.dist-info/entry_points.txt
qhrf_backend_selector-1.1.0.dist-info/top_level.txt
qhrf_backend_selector-1.1.0.dist-info/RECORD
