Metadata-Version: 2.4
Name: qhrf-backend-selector
Version: 1.1.0
Summary: Interactive IBM Quantum backend selector for QHRF experiments
Author-email: Zach White <Xses.Code@gmail.com>
License: MIT
Project-URL: Homepage, https://github.com/xs-es/qhrf-backend-selector
Project-URL: Documentation, https://github.com/xs-es/qhrf-backend-selector/blob/main/README.md
Project-URL: Repository, https://github.com/xs-es/qhrf-backend-selector.git
Project-URL: Bug Tracker, https://github.com/xs-es/qhrf-backend-selector/issues
Keywords: quantum computing,IBM Quantum,QHRF,quantum physics,backend selector
Classifier: Development Status :: 4 - Beta
Classifier: Intended Audience :: Science/Research
Classifier: License :: OSI Approved :: MIT License
Classifier: Operating System :: OS Independent
Classifier: Programming Language :: Python :: 3
Classifier: Programming Language :: Python :: 3.8
Classifier: Programming Language :: Python :: 3.9
Classifier: Programming Language :: Python :: 3.10
Classifier: Programming Language :: Python :: 3.11
Classifier: Programming Language :: Python :: 3.12
Classifier: Topic :: Scientific/Engineering :: Physics
Classifier: Topic :: Scientific/Engineering :: Artificial Intelligence
Requires-Python: >=3.8
License-File: LICENSE
Requires-Dist: qiskit-ibm-runtime>=0.17.0
Requires-Dist: qiskit>=0.45.0
Provides-Extra: dev
Requires-Dist: pytest>=7.0; extra == "dev"
Requires-Dist: black>=22.0; extra == "dev"
Requires-Dist: flake8>=5.0; extra == "dev"
Requires-Dist: mypy>=1.0; extra == "dev"
Dynamic: license-file
